farmhash.cp39-win32.pyd
farmhashpy-0.4.0.dist-info/LICENSE
farmhashpy-0.4.0.dist-info/METADATA
farmhashpy-0.4.0.dist-info/WHEEL
farmhashpy-0.4.0.dist-info/top_level.txt
farmhashpy-0.4.0.dist-info/RECORD
