Metadata-Version: 1.2
Name: farmhashpy
Version: 0.4.0
Summary: Google FarmHash Bindings for Python. Based on abandoned work by Veelion.
Home-page: https://github.com/openaristos/farmhashpy
Author: Isaac Elbaz
Author-email: ielbaz@openaristos.io
License: UNKNOWN
Keywords: farmhash,google
Platform: UNKNOWN
Classifier: Development Status :: 5 - Production/Stable
Classifier: License :: OSI Approved :: MIT License
Classifier: Intended Audience :: Developers
Classifier: Programming Language :: C
Classifier: Programming Language :: Python
Classifier: Programming Language :: Python :: 3.7
Classifier: Programming Language :: Python :: 3.8
Classifier: Programming Language :: Python :: 3.9
Requires-Python: >=3.7
